stamp/__init__.py
stamp/cdo.py
stamp/discovery.py
stamp/extract.py
stamp/fix.py
stamp/normalize.py
stamp/remediation.py
stamp/schema.py
stamp/trace.py
stamp/trace_schema.py
stamp/validate.py
stamp/cli/__init__.py
stamp/cli/fix.py
stamp/cli/main.py
stamp/cli/validate.py
waveframe_stamp-0.1.0.dist-info/licenses/LICENSE
waveframe_stamp-0.1.0.dist-info/METADATA
waveframe_stamp-0.1.0.dist-info/WHEEL
waveframe_stamp-0.1.0.dist-info/entry_points.txt
waveframe_stamp-0.1.0.dist-info/top_level.txt
waveframe_stamp-0.1.0.dist-info/RECORD
