Metadata-Version: 2.4
Name: waveframe-stamp
Version: 0.1.0
Summary: Schema-agnostic structural diagnostics engine for governed research artifacts.
Author-email: "Shawn C. Wright" <swright@waveframelabs.org>
License: Apache-2.0
Project-URL: Homepage, https://waveframelabs.org
Project-URL: Source, https://github.com/Waveframe-Labs/Waveframe-Stamp
Project-URL: Issues, https://github.com/Waveframe-Labs/Waveframe-Stamp/issues
Keywords: metadata,validation,governance,reproducibility,research,schema
Classifier: License :: OSI Approved :: Apache Software License
Classifier: Programming Language :: Python :: 3
Classifier: Programming Language :: Python :: 3 :: Only
Classifier: Programming Language :: Python :: 3.10
Classifier: Programming Language :: Python :: 3.11
Classifier: Programming Language :: Python :: 3.12
Classifier: Operating System :: OS Independent
Classifier: Intended Audience :: Developers
Classifier: Topic :: Software Development :: Quality Assurance
Classifier: Topic :: Software Development :: Libraries
Requires-Python: >=3.10
License-File: LICENSE
Requires-Dist: ruamel.yaml>=0.17.32
Requires-Dist: jsonschema>=4.19.0
Requires-Dist: typer>=0.12.0
Provides-Extra: dev
Requires-Dist: pytest>=7.0.0; extra == "dev"
Requires-Dist: pytest-cov>=4.0.0; extra == "dev"
Requires-Dist: black>=23.0.0; extra == "dev"
Requires-Dist: isort>=5.0.0; extra == "dev"
Requires-Dist: mypy>=1.0.0; extra == "dev"
Dynamic: license-file
